magic/__init__.py
magic/magic.py
magic/plot.py
magic/utils.py
magic/version.py
magic_impute-3.0.0.dist-info/METADATA
magic_impute-3.0.0.dist-info/WHEEL
magic_impute-3.0.0.dist-info/top_level.txt
magic_impute-3.0.0.dist-info/RECORD
