Metadata-Version: 2.1
Name: magic-impute
Version: 3.0.0
Summary: MAGIC
Home-page: https://github.com/KrishnaswamyLab/MAGIC
Author: 
Author-email: 
License: GNU General Public License Version 2
Download-URL: https://github.com/KrishnaswamyLab/MAGIC/archive/v3.0.0.tar.gz
Keywords: visualization,big-data,dimensionality-reduction,embedding,manifold-learning,computational-biology
Platform: UNKNOWN
Classifier: Development Status :: 5 - Production/Stable
Classifier: Environment :: Console
Classifier: Framework :: Jupyter
Classifier: Intended Audience :: Developers
Classifier: Intended Audience :: Science/Research
Classifier: Natural Language :: English
Classifier: Operating System :: MacOS :: MacOS X
Classifier: Operating System :: Microsoft :: Windows
Classifier: Operating System :: POSIX :: Linux
Classifier: Programming Language :: Python :: 2
Classifier: Programming Language :: Python :: 2.7
Classifier: Programming Language :: Python :: 3
Classifier: Programming Language :: Python :: 3.5
Classifier: Programming Language :: Python :: 3.6
Classifier: Topic :: Scientific/Engineering :: Bio-Informatics
Requires-Python: >=3.6
Requires-Dist: numpy (>=1.14.0)
Requires-Dist: scipy (>=1.1.0)
Requires-Dist: matplotlib
Requires-Dist: scikit-learn (>=0.19.1)
Requires-Dist: future
Requires-Dist: tasklogger (>=1.0.0)
Requires-Dist: graphtools (>=1.4.0)
Requires-Dist: pandas (>=0.25)
Requires-Dist: scprep (>=1.0)
Provides-Extra: doc
Requires-Dist: sphinx ; extra == 'doc'
Requires-Dist: sphinxcontrib-napoleon ; extra == 'doc'
Provides-Extra: test
Requires-Dist: nose2 ; extra == 'test'
Requires-Dist: anndata ; extra == 'test'
Requires-Dist: coverage ; extra == 'test'
Requires-Dist: coveralls ; extra == 'test'
